{
   "id": "p0000",
   "name": "Tyler Latham",
   "National ID": "123412341234",
   "Address of residence": "New York, USA",
   "Phonenum": "0881231234",
   "Email": "tyler@gmail.com",
   "Name of family member": "None",
   "Contact of family member": "None",
   "dob": "20/01/1990",
   "nationality": "American",
   "height": "180",
   "weight": "70",
   "bloodtype": "A+",
   "Insurance Provider": "None",
   "Insurance ID": "None",
   "Responsible Physician": "Dr. Timoty Tam",
   "Health-related behavior": "None",
   "Past medical records": "None",
   "Family history": "None",
   "Allergies": "Peanut",
   "Data of addmission": "15/06/2022",
   "Vaccination": "{'Received vaccine(1)': 'Pfizer', 'Received vaccine(2)': 'Pfizer', 'Received vaccine(3)': 'Pfizer'}",
   "Room": "104"
}